odoo10_addon_configuration_helper-10.0.1.0.0-py2.7-nspkg.pth
odoo/addons/configuration_helper/README.rst
odoo/addons/configuration_helper/__init__.py
odoo/addons/configuration_helper/__manifest__.py
odoo/addons/configuration_helper/i18n/am.po
odoo/addons/configuration_helper/i18n/ca.po
odoo/addons/configuration_helper/i18n/de.po
odoo/addons/configuration_helper/i18n/el_GR.po
odoo/addons/configuration_helper/i18n/es.po
odoo/addons/configuration_helper/i18n/fi.po
odoo/addons/configuration_helper/i18n/fr.po
odoo/addons/configuration_helper/i18n/gl.po
odoo/addons/configuration_helper/i18n/hr.po
odoo/addons/configuration_helper/i18n/hr_HR.po
odoo/addons/configuration_helper/i18n/it.po
odoo/addons/configuration_helper/i18n/nl.po
odoo/addons/configuration_helper/i18n/pt.po
odoo/addons/configuration_helper/i18n/pt_BR.po
odoo/addons/configuration_helper/i18n/sl.po
odoo/addons/configuration_helper/i18n/tr.po
odoo/addons/configuration_helper/i18n/zh_CN.po
odoo/addons/configuration_helper/models/__init__.py
odoo/addons/configuration_helper/models/config.py
odoo10_addon_configuration_helper-10.0.1.0.0.dist-info/DESCRIPTION.rst
odoo10_addon_configuration_helper-10.0.1.0.0.dist-info/METADATA
odoo10_addon_configuration_helper-10.0.1.0.0.dist-info/RECORD
odoo10_addon_configuration_helper-10.0.1.0.0.dist-info/WHEEL
odoo10_addon_configuration_helper-10.0.1.0.0.dist-info/metadata.json
odoo10_addon_configuration_helper-10.0.1.0.0.dist-info/namespace_packages.txt
odoo10_addon_configuration_helper-10.0.1.0.0.dist-info/top_level.txt
